CONTRIBUTORS
LICENSE
MANIFEST.in
README.rst
setup.cfg
setup.py
django_la_facebook.egg-info/PKG-INFO
django_la_facebook.egg-info/SOURCES.txt
django_la_facebook.egg-info/dependency_links.txt
django_la_facebook.egg-info/requires.txt
django_la_facebook.egg-info/top_level.txt
docs/Makefile
docs/TODO.rst
docs/background.rst
docs/callbacks.rst
docs/conf.py
docs/credits.rst
docs/goals.rst
docs/index.rst
docs/make.bat
docs/settings.rst
docs/test_project.rst
docs/usage.rst
la_facebook/__init__.py
la_facebook/access.py
la_facebook/admin.py
la_facebook/exceptions.py
la_facebook/la_fb_logging.py
la_facebook/models.py
la_facebook/urls.py
la_facebook/views.py
la_facebook/callbacks/__init__.py
la_facebook/callbacks/base.py
la_facebook/callbacks/default.py
la_facebook/templatetags/__init__.py
la_facebook/templatetags/la_facebook_tags.py
la_facebook/tests/__init__.py
la_facebook/tests/test_access_module.py
la_facebook/tests/test_callbacks.py
la_facebook/tests/test_models.py
la_facebook/tests/test_views.py
la_facebook/tests/urls.py
la_facebook/tests/views.py
la_facebook/utils/__init__.py
la_facebook/utils/anyetree.py
la_facebook/utils/loader.py
test_project/__init__.py
test_project/manage.py
test_project/settings.py
test_project/urls.py
test_project/connect/__init__.py
test_project/connect/models.py
test_project/connect/urls.py
test_project/connect/views.py
test_project/connect/fixtures/initial_data.json
test_project/connect/templates/after.html
test_project/connect/templates/fbinfo.html
test_project/connect/templates/index.html
test_project/connect/templates/registration/login.html
test_project/connect/tests/__init__.py
test_project/connect/tests/test_connect.py
test_project/connect/tests/utils.py