Metadata-Version: 1.0
Name: django-la-facebook
Version: 0.1.1
Summary: Definitive facebook auth for Django
Home-page: http://github.com/cartwheelweb/django-la-facebook
Author: pydanny
Author-email: pydanny@pydanny.com
License: BSD
Platform: UNKNOWN
Classifier: Development Status :: 5 - Production/Stable
Classifier: Environment :: Web Environment
Classifier: Intended Audience :: Developers
Classifier: License :: OSI Approved :: BSD License
Classifier: Operating System :: OS Independent
Classifier: Programming Language :: Python
Classifier: Framework :: Django
